---
title: 4.3 çº¿ç¨‹é—´é€šä¿¡
order: "3"
chapter: "4"
---

## 4.3 çº¿ç¨‹é—´é€šä¿¡

å¾ˆå¤šæ–¹å¼éƒ½å¯ä»¥å®ç°çº¿ç¨‹ä¹‹é—´é€šä¿¡ã€‚æ¯”å¦‚åœ¨ä¹‹å‰æˆ‘ä»¬ä»‹ç»è¿‡çš„volatileè¿˜æœ‰synchronizedå…³é”®å­—ã€‚è¿™äº›éƒ½èƒ½ä¿è¯æˆ‘åšè¿‡çš„ä¸€äº›ä¿®æ”¹æ˜¯å¯¹å…¶å®ƒçº¿ç¨‹ç«‹å³å¯è§çš„ã€‚é™¤äº†è¿™äº›ï¼Œå…¶å®ƒçš„æœºåˆ¶æ¯”å¦‚wait/notifyæœºåˆ¶è¿˜æœ‰ç®¡é“ç­‰ç­‰ä¹Ÿéƒ½å¯ä»¥ã€‚

### 4.3.1 volatile & synchronized

ä¸Šä¸€èŠ‚ï¼Œæˆ‘ä»¬ä»‹ç»çš„é‚£ä¸ªä¸­æ­¢çº¿ç¨‹çš„ä¾‹å­ï¼š[[Study Log/java_kotlin_study/concurrency_art/4_2_thread_life#4.2.5 å®‰å…¨åœ°ç»ˆæ­¢çº¿ç¨‹|4_2_thread_life]]ã€‚é‡Œé¢çš„å˜é‡`on`å°±æ˜¯volatileçš„å˜é‡ã€‚å®ƒèƒ½å¤Ÿä¿è¯ï¼Œæˆ‘å†™å…¥çš„è¿™ä¸ªå€¼èƒ½å¤Ÿç«‹åˆ»è¢«å…¶ä»–çº¿ç¨‹çœ‹åˆ°ã€‚è¿˜æœ‰[[Study Log/java_kotlin_study/concurrency_art/3_4_volatile_mm_semantics#^d00fb6|3_4_volatile_mm_semantics]]é‡Œé¢æˆ‘ä»¬è¡¥å……çš„ä¾‹å­ï¼Œä¹Ÿéƒ½æ˜¯è¿™æ ·çš„é“ç†ã€‚

ç„¶åæ˜¯synchronizedã€‚ä¹‹å‰æˆ‘ä»¬å·²ç»ä»‹ç»è¿‡äº†ã€‚è¿™é‡Œç»™ä¸€ä¸ªä¾‹å­ï¼š

```java
public class SynchronizedExample2 {
    public static void main(String[] args) {
        synchronized (SynchronizedExample2.class) {

        }
        m();
    }

    public static synchronized void m() {

    }
}
```

ç¼–è¯‘å®Œæˆåï¼Œæ‰§è¡Œ

```shell
javap -v SynchronizedExample2.class
```

ä¼šå¾—åˆ°å¦‚ä¸‹è¾“å‡ºï¼š

```shell
  #16 = Utf8               SourceFile
  #17 = Utf8               SynchronizedExample2.java
  #18 = NameAndType        #5:#6          // "<init>":()V
  #19 = Utf8               concurrency/itc/SynchronizedExample2
  #20 = NameAndType        #15:#6         // m:()V
  #21 = Utf8               java/lang/Object
  #22 = Utf8               [Ljava/lang/String;
  #23 = Utf8               java/lang/Throwable
{
  public concurrency.itc.SynchronizedExample2();
    descriptor: ()V
    flags: ACC_PUBLIC
    Code:
      stack=1, locals=1, args_size=1
         0: aload_0
         1: invokespecial #1                  // Method java/lang/Object."<init>":()V
         4: return
      LineNumberTable:
        line 3: 0

  public static void main(java.lang.String[]);
    descriptor: ([Ljava/lang/String;)V
    flags: ACC_PUBLIC, ACC_STATIC
    Code:
      stack=2, locals=3, args_size=1
         0: ldc           #2                  // class concurrency/itc/SynchronizedExample2
         2: dup
         3: astore_1
         4: monitorenter                      # synchronizedçš„å…¥å£ä½ç½®
         5: aload_1
         6: monitorexit
         7: goto          15
        10: astore_2
        11: aload_1
        12: monitorexit
        13: aload_2
        14: athrow
        15: invokestatic  #3                  // Method m:()V
        18: return
      Exception table:
         from    to  target type
             5     7    10   any
            10    13    10   any
      LineNumberTable:
        line 5: 0
        line 7: 5
        line 8: 15
        line 9: 18
      StackMapTable: number_of_entries = 2
        frame_type = 255 /* full_frame */
          offset_delta = 10
          locals = [ class "[Ljava/lang/String;", class java/lang/Object ]
          stack = [ class java/lang/Throwable ]
        frame_type = 250 /* chop */
          offset_delta = 4

  public static synchronized void m();
    descriptor: ()V
    flags: ACC_PUBLIC, ACC_STATIC, ACC_SYNCHRONIZED    # ACC_SYNCHRONIZEDä»£è¡¨synchronizedæ–¹æ³•
    Code:
      stack=0, locals=0, args_size=0
         0: return
      LineNumberTable:
        line 13: 0
}
SourceFile: "SynchronizedExample2.java"
```

å¯ä»¥çœ‹åˆ°ï¼Œsynchronizedå—æ˜¯ç”¨`monitorenter`å’Œ`monitorexit`æ¥è¡¨ç¤ºçš„ï¼›è€Œsynchronizedæ–¹æ³•æ˜¯ç”¨`ACC_SYNCHRONIZED`è¡¨ç¤ºçš„ã€‚å½“ç„¶ï¼Œè¿™ä¸¤ç§æ–¹å¼çš„æœ€ç»ˆç»“æœä¹Ÿéƒ½æ˜¯`monitorenter`å’Œ`monitorexit`ã€‚

> ä»»æ„ä¸€ä¸ªå¯¹è±¡éƒ½æ‹¥æœ‰è‡ªå·±çš„ç›‘è§†å™¨ï¼Œå½“è¿™ä¸ªå¯¹è±¡ç”±åŒæ­¥å—æˆ–è€…è¿™ä¸ªå¯¹è±¡çš„åŒæ­¥æ–¹æ³•è°ƒç”¨æ—¶ï¼Œæ‰§è¡Œæ–¹æ³•çš„çº¿ç¨‹å¿…é¡»å…ˆè·å–åˆ°è¯¥å¯¹è±¡çš„ç›‘è§†å™¨æ‰èƒ½è¿›å…¥åŒæ­¥å—æˆ–è€…åŒæ­¥æ–¹æ³•ï¼Œè€Œæ²¡æœ‰è·å–åˆ°ç›‘è§†å™¨ï¼ˆæ‰§è¡Œè¯¥æ–¹æ³•ï¼‰çš„çº¿ç¨‹å°†ä¼šè¢«é˜»å¡åœ¨åŒæ­¥å—å’ŒåŒæ­¥æ–¹æ³•çš„å…¥å£å¤„ï¼Œè¿›å…¥ BLOCKED çŠ¶æ€

monitorçš„ç­‰å¾…åŒæ­¥æœºåˆ¶å¦‚ä¸‹å›¾ï¼š

![[Study Log/java_kotlin_study/concurrency_art/resources/Drawing 2024-02-12 21.07.53.excalidraw.png]]

ä¸€ä¸ªçº¿ç¨‹åœ¨è¯•å›¾è·å–Monitoré”çš„æ—¶å€™ï¼Œã€å¯èƒ½ã€ä¼šç»å†å¦‚ä¸‹è¿‡ç¨‹ï¼š

1. è¿›å…¥synchronizedå—ï¼Œè°ƒç”¨`monitorenter`ï¼Œå°è¯•è·å–Monitoré”ï¼›
2. å› ä¸ºå…¶å®ƒçº¿ç¨‹å·²ç»è·å¾—äº†Monitoré”ï¼Œæ‰€ä»¥è·å–å¤±è´¥äº†ã€‚æ­¤æ—¶è¿›å…¥<mark class="square-solid-yellow">åŒæ­¥é˜Ÿåˆ—</mark>ï¼ˆSynchronized Queueï¼‰ï¼ŒçŠ¶æ€å˜ä¸º**BLOCKED**ï¼›
3. å½“è®¿é—®Objectçš„å‰é©±ï¼ˆè·å¾—äº†é”çš„çº¿ç¨‹ï¼‰é‡Šæ”¾äº†é”ï¼Œè¿™ä¸ª**BLOCKED**çš„çº¿ç¨‹è¢«å”¤é†’ï¼Œå¹¶é‡æ–°å°è¯•è·å–é”è¿›å…¥ï¼›
4. æˆåŠŸè·å¾—äº†Monitoré”ï¼Œæ‰§è¡ŒåŒæ­¥ä»£ç ï¼›
5. æ‰§è¡Œå®Œæ¯•ï¼Œé‡Šæ”¾äº†é”ï¼Œå¹¶é€šçŸ¥<mark class="square-solid-yellow">åŒæ­¥é˜Ÿåˆ—</mark>ä¸­å‰©ä¸‹çš„äººã€‚

### 4.3.2 Wait & Notify

ä¹‹å‰æˆ‘å†™è¿‡ä¸€ä¸ªä¾‹å­ï¼š[[Study Log/java_kotlin_study/java_kotlin_study_diary/lock_in_java|lock_in_java]]ã€‚å­¦ä¹ å®Œæœ¬èŠ‚ä¹‹åï¼Œå¯ä»¥å†å›é¡¾ä¸€ä¸‹ã€‚

ä¹¦ä¸Šç»™äº†ä¸€ä¸ªè½®è¯¢å»æŸ¥è¯¢çš„ä¾‹å­ã€‚ç„¶åè¯´è¿™ç§è½®è¯¢çš„æ–¹å¼å±äºå¿™ç­‰å¾…ï¼Œæµªè´¹æ•ˆç‡ï¼Œä»è€Œå¼•å‡ºWait \& Notifyæœºåˆ¶ã€‚å…¶å®ï¼Œè¿™ç§æƒ…å†µæˆ‘åœ¨ä»‹ç»æ“ä½œç³»ç»Ÿçš„æ—¶å€™å°±å·²ç»è¯´è¿‡äº†ï¼š[[Lecture Notes/Operating System/os#3.3 How to avoid race conditions?|os]]ã€‚åªä¸è¿‡å½“æ—¶è¯´çš„æ˜¯è¿›ç¨‹ä¹‹é—´çš„ã€‚

> ä¹¦ä¸Šç»™çš„ï¼Œè½®è¯¢çš„å…·ä½“çš„ç¼ºç‚¹å¦‚ä¸‹ï¼š
> 
> 1. éš¾ä»¥ç¡®ä¿åŠæ—¶æ€§ã€‚åœ¨ç¡çœ æ—¶ï¼ŒåŸºæœ¬ä¸æ¶ˆè€—å¤„ç†å™¨èµ„æºï¼Œä½†æ˜¯å¦‚æœç¡å¾—è¿‡ä¹…ï¼Œå°±ä¸èƒ½åŠæ—¶å‘ç°æ¡ä»¶å·²ç»å˜åŒ–ï¼Œä¹Ÿå°±æ˜¯åŠæ—¶æ€§éš¾ä»¥ä¿è¯ã€‚
> 2. éš¾ä»¥é™ä½å¼€é”€ã€‚å¦‚æœé™ä½ç¡çœ çš„æ—¶é—´ï¼Œæ¯”å¦‚ä¼‘çœ  1 æ¯«ç§’ï¼Œè¿™æ ·æ¶ˆè´¹è€…èƒ½æ›´åŠ è¿…é€Ÿåœ°å‘ç°æ¡ä»¶å˜åŒ–ï¼Œä½†æ˜¯å´å¯èƒ½æ¶ˆè€—æ›´å¤šçš„å¤„ç†å™¨èµ„æºï¼Œé€ æˆäº†æ— ç«¯çš„æµªè´¹ã€‚

ä¸wait \& notifyæœ‰å…³çš„æ–¹æ³•å®šä¹‰åœ¨Objectä¸­ï¼Œæ‰€æœ‰Javaå¯¹è±¡éƒ½å…·å¤‡ï¼š

|     æ–¹æ³•åç§°      | æè¿°                                                                                                                         |
|:-----------------:| ---------------------------------------------------------------------------------------------------------------------------- |
|    `notify()`     | é€šçŸ¥ä¸€ä¸ªåœ¨å¯¹è±¡ä¸Šç­‰å¾…çš„çº¿ç¨‹ï¼Œä½¿å…¶ä»`wait()`æ–¹æ³•**è¿”å›**ï¼Œè€Œè¿”å›çš„å‰ææ˜¯**è¯¥çº¿ç¨‹è·å–åˆ°äº†å¯¹è±¡çš„é”**ã€‚                           |
|   `notifyAll()`   | é€šçŸ¥æ‰€æœ‰ç­‰å¾…åœ¨è¯¥å¯¹è±¡ä¸Šçš„çº¿ç¨‹ã€‚                                                                                               |
|     `wait()`      | è°ƒç”¨è¯¥æ–¹æ³•çš„çº¿ç¨‹è¿›å…¥**WAITING**çŠ¶æ€ï¼Œåªæœ‰ç­‰å¾…å¦å¤–çº¿ç¨‹çš„é€šçŸ¥æˆ–è¢«ä¸­æ–­æ‰ä¼šè¿”å›ã€‚éœ€è¦æ³¨æ„ï¼Œ è°ƒç”¨`wait()`æ–¹æ³•åï¼Œä¼šé‡Šæ”¾å¯¹è±¡çš„é”ã€‚ |
|   `wait(long)`    | è¶…æ—¶ç­‰å¾…ä¸€æ®µæ—¶é—´ã€‚è¿™é‡Œçš„å‚æ•°æ—¶é—´æ˜¯æ¯«ç§’ï¼Œä¹Ÿå°±æ˜¯ç­‰å¾…é•¿è¾¾næ¯«ç§’ï¼Œå¦‚æœæ²¡æœ‰é€šçŸ¥å°±è¶…æ—¶è¿”å›ã€‚                                        |
| `wait(long, int)` | å¯¹äºè¶…æ—¶æ—¶é—´æ›´ç»†ç²’åº¦çš„æ§åˆ¶ï¼Œå¯ä»¥è¾¾åˆ°çº³ç§’ã€‚                                                                                   |

> [!info]
> çº¿ç¨‹çš„çŠ¶æ€ï¼š[[Study Log/java_kotlin_study/concurrency_art/4_1_thread_basic#4.1.2 çº¿ç¨‹çš„çŠ¶æ€|4_1_thread_basic]]

æˆ‘ä»¬å°†æ¼”ç¤ºä¸‹é¢çš„ä¾‹å­ï¼Œæ¥è¯´æ˜è¿™äº›æ–¹æ³•çš„åŠŸèƒ½ï¼š ^f936d3

1. çº¿ç¨‹waitThreadè·å–äº†é”lockï¼Œå¹¶åœ¨è·å–é”ä¹‹å**ä¸æ–­**æ‰§è¡Œwaitã€‚è¿™ä¼šå¯¼è‡´waitThreadè¿›å…¥WATIINGçŠ¶æ€å¹¶**é‡Šæ”¾lock**ï¼›
2. éšåçº¿ç¨‹notifyThreadä¹Ÿè·å–äº†lockï¼Œå¹¶è·å–æˆåŠŸã€‚å› ä¸ºwaitThreadç”±äºwaitå·²ç»é‡Šæ”¾äº†lockã€‚ä¹‹åï¼ŒnotifyThreadä¼šé€šçŸ¥waitThreadå¯ä»¥è·å–lockï¼ŒåŒæ—¶**ä¸éœ€è¦å†ä¸æ–­**æ‰§è¡Œwaitäº†ï¼›
3. ä½†æ˜¯ç”±äºæ­¤æ—¶notifyThreadè¿˜éœ¸å ç€lockï¼ˆä¸ºä»€ä¹ˆå‘¢ï¼Ÿå› ä¸ºæˆ‘ä¹æ„ï¼å°±æ˜¯æ•…æ„éœ¸å ä¸é‡Šæ”¾ã€‚å…·ä½“çš„è¡Œä¸ºçœ‹æœ€åçš„å›¾ï¼ŒæŒ‰ç€åºå·æ¥ç†è§£å°±å¾ˆå®¹æ˜“äº†ï¼‰ï¼Œæ‰€ä»¥waitThreadå¹¶ä¸ä¼šä»waitè¿”å›ï¼›
4. ä¹‹åï¼ŒnotifyThreadä¼šçŸ­æš‚é‡Šæ”¾lockå¹¶å¿«é€Ÿå†æ¬¡è·å–lockã€‚åœ¨çŸ­æš‚é‡Šæ”¾ä¹‹åï¼ŒwaitThreadå°±æœ‰æœºä¼šå»æŠ¢lockäº†ã€‚ä½†æ˜¯ï¼Œç”±äºnotifyThreadåˆä¼šå¿«é€Ÿé‡æ–°è·å–lockï¼Œæ‰€ä»¥æ­¤æ—¶å­˜åœ¨ç«äº‰ï¼š
	1. å¦‚æœnotifyThreadé‡æ–°è·å–åˆæˆåŠŸäº†ï¼Œé‚£ä¹ˆæ­¤æ—¶waitThreadè¿˜æ˜¯æ— æ³•è¿”å›ã€‚åªæœ‰ç­‰notifyThreadå†æ¬¡é‡Šæ”¾lockä¹‹åæ‰èƒ½è·å–ï¼›
	2. å¦‚æœwaitThreadæŠ¢åˆ°äº†lockï¼Œé‚£ä¹ˆç”±äº2ä¸­notifyThreadé€šçŸ¥æˆ‘ä¸è¦å†ä¸æ–­æ‰§è¡Œwaitäº†ï¼Œæˆ‘å°†ä¼šä¸å†ç­‰å¾…ï¼Œç»§ç»­è¿›è¡Œä¸‹å»ï¼›
5. æ ¹æ®4.1å’Œ4.2ï¼Œä¹Ÿä¼šæœ‰ä¸¤ç§ç»“å±€ï¼š 
	1. å¦‚æœ4.1å‘ç”Ÿäº†ï¼Œé‚£ä¹ˆnotifyThreadå†æ¬¡é‡Šæ”¾lockä¹‹åï¼ŒwaitThreadæ‰èƒ½é‡æ–°æŠ¢åˆ°lockï¼Œæ‰§è¡Œ4.2ä¸­çš„å†…å®¹ï¼›
	2. å¦‚æœ4.2å‘ç”Ÿäº†ï¼Œé‚£ä¹ˆnotifyThreadä¼šç­‰åˆ°waitThreadé‡Šæ”¾é”ä¹‹åæ‰§è¡Œ4.1ä¸­å†æ¬¡è·å¾—lockçš„è¡Œä¸ºã€‚

é¦–å…ˆï¼Œæ˜¯ä¸€äº›æ ‡å¿—ä½å’Œå·¥å…·æ–¹æ³•ï¼š

```kotlin
companion object {
	@JvmField
	var needWait = true

	@JvmField
	var lock = Object()

	@JvmStatic
	fun getDate(): String {
		return SimpleDateFormat("HH:mm:ss").format(Date())
	}

	@JvmStatic
	fun log(msg: String) {
		println("${Thread.currentThread()} $msg ${getDate()}")
	}
}
```

ç„¶åæ˜¯ç­‰å¾…çº¿ç¨‹waitThreadã€‚å†…å®¹å¦‚ä¸‹ï¼š

1. è·å–lockï¼›
2. åªè¦needWaitï¼Œå°±ä¸åœèµ°å¾ªç¯ã€‚æ¯æ¬¡å¾ªç¯è¿›è¡Œä¸€æ¬¡waitï¼›
3. å¾ªç¯é€€å‡ºä¹‹åï¼Œç»§ç»­æ‰§è¡Œå‰©ä¸‹çš„å·¥ä½œã€‚

```kotlin
class Wait : Runnable {  
    override fun run() {  
        synchronized(lock) {                                // 1
            while (needWait) {                             // 2
                try {  
                    log("need wait. wa @")  
                    lock.wait()  
                } catch (_: InterruptedException) {  
  
                }  
            }  
            log("running @")                                // 3
        }  
    }  
}
```

é€šçŸ¥çº¿ç¨‹notifyThreadçš„å†…å®¹å¦‚ä¸‹ï¼š

1. è·å–lockï¼›
2. åœ¨lockä¸­ï¼Œé€šçŸ¥waitThreadï¼Œå¹¶needWaitç½®ä¸ºfalseï¼›
3. åœ¨é‡Šæ”¾é”ä¹‹å‰å…ˆç¡5sã€‚è¿™æ˜¯ä¸ºäº†å±•ç¤ºï¼ŒnotifyThreadä¸é‡Šæ”¾é”ï¼ŒwaitThreadå°±æ— æ³•ä»waitè¿”å›ï¼›
4. é‡Šæ”¾é”ä¹‹åï¼Œå†æ¬¡å°è¯•è·å–lockã€‚

```kotlin
class Notify : Runnable {
	override fun run() {
		synchronized(lock) {                          // 1
			log("hold lock. notify @")
			lock.notifyAll()
			needWait = false                         // 2
			SleepUtils.second(5)                     // 3
		}
		synchronized(lock) {                          // 4
			log("hold lock again. sleep @")
			SleepUtils.second(5)
		}
	}
}
```

æµ‹è¯•ç¨‹åºå¦‚ä¸‹ï¼š

```kotlin
fun main() {
    val waitThread = Thread(WaitNotify.Wait(), "WaitThread")
    waitThread.start()
    TimeUnit.SECONDS.sleep(1)
    val notifyThread = Thread(WaitNotify.Notify(), "NotifyThread")
    notifyThread.start()
}
```

æ ·ä¾‹è¾“å‡ºï¼š

```shell
Thread[WaitThread,5,main] need wait. wa @ 22:32:20
Thread[NotifyThread,5,main] hold lock. notify @ 22:32:21
Thread[NotifyThread,5,main] hold lock again. sleep @ 22:32:26
Thread[WaitThread,5,main] running @ 22:32:31
```

ä¸‹é¢å¯¹è¿™ä¸ªç»“æœä¸­çš„é—®é¢˜ä½œå‡ºè§£ç­”ã€‚

- [?] *ä¸ºä»€ä¹ˆå‰ä¸¤è¡Œä¹‹é—´å·®äº†ä¸€ç§’é’Ÿï¼Ÿ*
- [>] æˆ‘ä»¬åœ¨æµ‹è¯•ç¨‹åºä¸­é—´sleepäº†ä¸€ç§’é’Ÿã€‚è¿™ä¹Ÿå°±å¯¼è‡´äº†waitThreadåœ¨waitä¹‹åé‡Šæ”¾äº†lockï¼Œåˆè¿‡äº†1sä¹‹ånotifyThreadæ‰å¯åŠ¨å¹¶è·å–lockã€‚
- [?] *ä¸ºä»€ä¹ˆ2å’Œ3ä¹‹é—´å·®äº†5ç§’é’Ÿï¼Ÿ*
- [>] å› ä¸ºnotifyThreadåœ¨ç¬¬ä¸€æ¬¡è·å–lockä¹‹åç¡çœ äº†5sã€‚å®ƒæ²¡é‡Šæ”¾ï¼ŒwaitThreadå’ŒnotifyThreadéƒ½æ˜¯æ²¡æ³•ç»§ç»­ä¸‹å»çš„ã€‚
- [?] *æœ€åä¸¤è¡Œè¾“å‡ºå¯èƒ½äº¤æ¢å—ï¼Ÿ*
- [>] å¯èƒ½ã€‚å°±æ˜¯å–å†³äº[[#^f936d3|ä¹‹å‰]]çš„4.1å’Œ4.2å“ªä¸ªå…ˆæ‰§è¡Œã€‚
- [?] *ä¸ºä»€ä¹ˆ`needWait`ä¸æ˜¯volatileçš„ï¼Ÿ*
- [>] å› ä¸ºåœ¨synchronizedä¸­ã€‚synchronizedæœ¬èº«å°±åŒ…æ‹¬volatileæ‰€æœ‰çš„è¯­ä¹‰ï¼Œæ‰€ä»¥ä¸éœ€è¦äº†ã€‚

[[#^f936d3|ä¹‹å‰]]çš„ä¾‹å­ï¼Œå›¾ç¤ºå¦‚ä¸‹ï¼š

![[Study Log/java_kotlin_study/concurrency_art/resources/Drawing 2024-02-12 23.18.16.excalidraw.png]]

è¿™é‡Œé¢æ ‡äº†æ•°å­—çš„åœ°æ–¹éƒ½æ˜¯å’Œå‰é¢å¯¹åº”çš„ã€‚å”¯ä¸€éœ€è¦è§£é‡Šçš„å°±æ˜¯**çº¢è‰²çš„ä¸¤ä¸ª4**ã€‚è¿™é‡Œåœ¨æè¿°çš„æ˜¯waitThreadåœ¨åŒæ­¥é˜Ÿåˆ—ä¸­å’ŒnotifyThreadæŠ¢é”çš„æƒ…å†µã€‚å¦‚æœåŒæ­¥é˜Ÿåˆ—ä¸­çš„waitThreadæŠ¢åˆ°äº†ï¼Œé‚£ä¹ˆnotifyThreadè¦èµ°Enter failureï¼Œä¹Ÿè¦è¿›å…¥åˆ°åŒæ­¥é˜Ÿåˆ—ä¸­ï¼›å¦‚æœnotifyThreadæŠ¢åˆ°äº†ï¼Œé‚£ä¹ˆwaitThreadä¼šèµ°Enter failureã€‚

> [!summary] æœ€åï¼Œä¹¦ä¸Šçš„æ€»ç»“ã€‚é‡è¦çš„ç‚¹å¦‚ä¸‹ï¼š
> 1. `wait()` `notify()` `notifyAll()`çš„ä½¿ç”¨å¿…é¡»è¦å…ˆsynchronizedï¼›
> 2. è°ƒç”¨ `wait()`æ–¹æ³•åï¼Œçº¿ç¨‹çŠ¶æ€ç”± **RUNNING** å˜ä¸º **WAITING**ï¼Œå¹¶å°†å½“å‰çº¿ç¨‹æ”¾ç½®åˆ°å¯¹è±¡çš„ç­‰å¾…é˜Ÿåˆ—ï¼›
> 3. `notify()`æˆ– `notifyAll()`æ–¹æ³•è°ƒç”¨åï¼Œç­‰å¾…çº¿ç¨‹ä¾æ—§ä¸ä¼šä»`wait()`è¿”å›ï¼Œéœ€è¦è°ƒç”¨`notify()`æˆ–`notifAll()`çš„çº¿ç¨‹**é‡Šæ”¾é”ä¹‹å**ï¼Œç­‰å¾…çº¿ç¨‹æ‰æœ‰æœºä¼šä» wait()è¿”å›ï¼›
> 4. `notify()`æ–¹æ³•å°†ç­‰å¾…é˜Ÿåˆ—ä¸­çš„ä¸€ä¸ªç­‰å¾…çº¿ç¨‹ä»ç­‰å¾…é˜Ÿåˆ—ä¸­ç§»åˆ°åŒæ­¥é˜Ÿåˆ—ä¸­ï¼Œè€Œ`notifyAll()`æ–¹æ³•åˆ™æ˜¯å°†ç­‰å¾…é˜Ÿåˆ—ä¸­æ‰€æœ‰çš„çº¿ç¨‹å…¨éƒ¨ç§»åˆ°åŒæ­¥é˜Ÿåˆ—ï¼Œè¢«ç§»åŠ¨çš„çº¿ç¨‹çŠ¶æ€ç”± **WAITING** å˜ä¸º **BLOCKED**ï¼›
> 5. ä»`wait()`æ–¹æ³•è¿”å›çš„å‰ææ˜¯è·å¾—äº†è°ƒç”¨å¯¹è±¡çš„é”ã€‚
> 
> ---
> 
> **wait \& notifyçš„ç»å…¸èŒƒå¼ï¼š**
> 
> - ç­‰å¾…æ–¹ï¼š
> 
> ~~~kotlin
> synchronized(object) {
> 	while (needWait) {
> 		object.wait()
> 	}
> 	doSomething()
> }
> ~~~
> 
> - é€šçŸ¥æ–¹ï¼š
> 
> ~~~kotlin
> synchronized(object) {
> 	needWait = false
> 	object.notifyAll()
> }
> ~~~

> [!note]
> æˆ‘ä»¬å¯ä»¥å‘ç°ï¼Œsynchronizedå’Œwait \& notifyçš„ç»“åˆåº¦æ˜¯éå¸¸ç´§å¯†çš„ã€‚å®é™…ä¸Šï¼Œå®ƒä»¬ä¿©åœ¨JVMä¸­çš„å®ç°æœ¬èº«ä¹Ÿæ˜¯åœ¨åŒä¸€ä¸ªç±»ä¸­å»ç®¡ç†çš„ã€‚
> 
> è§`jdk/src/hotspot/share/runtime/objectMonitor.hpp`ã€‚ç±»çš„å¼€å¤´ä¹Ÿæœ‰ä¸€å †æ³¨é‡Šè¯´æ˜è¿™å¥—æœºåˆ¶çš„ä½œç”¨ã€‚è®²è§£ï¼š[synchronizedåº•å±‚å®ç°monitorè¯¦è§£ - æœ±å­å¨ - åšå®¢å›­](https://www.cnblogs.com/minikobe/p/12123065.html)
> 
> é‡Œé¢çš„`_WaitSet`å°±æ˜¯æˆ‘ä»¬ä¸Šé¢è¯´çš„Wait Queueï¼›`_EntryList`å°±æ˜¯Synchronized Queueã€‚

> - [ ] #TODO tasktodo1715341210942 æä¸ªä½ä¼˜ä»»åŠ¡ï¼ŒæŠŠhotspoté‡Œè¿™å—ææ˜ç™½ã€‚ ğŸ”½ â• 2024-05-10

---

å¯¹äºä¹‹å‰é‚£ä¸ªäº¤æ›¿æ‰“å°çš„ä¾‹å­ï¼š[[Study Log/java_kotlin_study/java_kotlin_study_diary/lock_in_java#1-100|lock_in_java]]ï¼Œæˆ‘å†™äº†ä¸€ä¸ªæ›´ç®€å•çš„ç‰ˆæœ¬ï¼š

```kotlin
class OneToHundred {

    companion object {
        private val lock = Object()
        private var currThread = 1
        private var currNum = 1
        private val Int.next: Int
            get() = if (this == 3) 1 else this + 1
        private var isRunning = true
    }

    private val th1 = Thread(PrintRunnable(1))
    private val th2 = Thread(PrintRunnable(2))
    private val th3 = Thread(PrintRunnable(3))

    fun start() {
        th1.start()
        th2.start()
        th3.start()
    }

    class PrintRunnable(private val thNum: Int) : Runnable {
        override fun run() {
            while (currNum <= 100) {
                synchronized(lock) {
                    while (currThread != thNum && isRunning) {
                        try {
                            lock.wait()
                        } catch (_: InterruptedException) {}
                    }
                    if (currNum == 100) {
                        isRunning = false
                    } else if (currNum > 100) {
                        return
                    }
                    println("th${thNum}: ${currNum++}")
                    lock.notifyAll()
                    currThread = currThread.next
                }
            }
        }
    }
}
```

è¿™ä¸ªä¾‹å­ä¸­çš„ä»»ä½•ä¸€ä¸ªåœ°æ–¹å»æ‰ï¼Œéƒ½æ— æ³•æ­£å¸¸è¾“å‡º1-100æˆ–è€…æ— æ³•æ­£å¸¸ç»“æŸã€‚

### 4.3.3 Piped IO

ä¸»è¦çš„ç±»å¦‚ä¸‹ï¼š

* å­—èŠ‚å‹
	* PipedOutputStream
	* PipedInputStream
* å­—ç¬¦å‹
	* PipedReader
	* PipedWriter

ä¸‹é¢æ˜¯ä¸€ä¸ªä¾‹å­ï¼š

```kotlin
class Piped {
    class Print(private val reader: PipedReader) : Runnable {
        override fun run() {
            var receive = 0
            try {
                receive = reader.read()
                while (receive != -1) {
                    print(receive.toChar())
                    receive = reader.read()
                }
            } catch (_: IOException) {}
        }
    }
}

fun main() {
    val writer = PipedWriter()
    val reader = PipedReader()
    writer.connect(reader)
    val printThread = Thread(Piped.Print(reader), "PrintThread")
    printThread.start()
    var ch = 0
    writer.use {
        ch = System.`in`.read()
        while (ch != -1) {
            it.write(ch)
            ch = System.`in`.read()
        }
    }
}
```

> `writer.connect(reader)`å»ºç«‹äºŒè€…çš„è¿æ¥ã€‚äºŒè€…ä¸å¤„äºè¿æ¥çŠ¶æ€æ—¶ï¼Œ***==readerå¤„äºé˜»å¡çŠ¶æ€==***ï¼›

### 4.3.4 Thread.join

joinçš„ä½¿ç”¨éå¸¸ç®€å•ã€‚**å½“å‰çº¿ç¨‹ç­‰å¾…è°ƒç”¨joinçš„çº¿ç¨‹ç»ˆæ­¢åï¼Œå½“å‰çº¿ç¨‹æ‰èƒ½ä»joinè¿”å›**ã€‚

```kotlin
class Domino(private val previous: Thread) : Runnable {
	override fun run() {
		try {
			previous.join()
		} catch (_: InterruptedException) {}
		println("${Thread.currentThread().name} terminate.")
	}
}
```

åœ¨å½“å‰ä¾‹å­ä¸­ï¼Œæ„å»ºä¸€ä¸ªçº¿ç¨‹éœ€è¦ä¼ å…¥ä¸€ä¸ªå‰é©±çº¿ç¨‹ã€‚å½“å‰çº¿ç¨‹ç­‰å¾…å‰é©±çº¿ç¨‹ç»“æŸä¹‹åï¼Œå½“å‰çº¿ç¨‹æ‰èƒ½è¿”å›ã€‚æˆ‘ä»¬åˆ¶ä½œè¿™æ ·ä¸€ä¸ªç­‰å¾…é“¾ï¼š

```mermaid
graph RL
th0 --> main
th1 --> th0
th2 --> th1
th3 --> th2
... --> th3
th9 --> ...
```

å›¾ä¸­çš„ç®­å¤´è¡¨ç¤ºç­‰å¾…å…³ç³»ã€‚th0ä¼šç­‰å¾…mainç»“æŸï¼Œth1ä¼šç­‰å¾…th0ç»“æŸï¼Œä»¥æ­¤ç±»æ¨ã€‚

å› æ­¤ï¼Œåªæœ‰mainç»“æŸä¹‹åï¼Œå…¶å®ƒçº¿ç¨‹æ‰æœ‰å¯èƒ½ç»§ç»­è¿›è¡Œä¸‹å»ã€‚æ‰€ä»¥ï¼Œæˆ‘ä»¬åœ¨mainçº¿ç¨‹ç»“æŸä¹‹å‰ä¼‘çœ 5sï¼Œé‚£ä¹ˆæ‰€æœ‰çš„çº¿ç¨‹ä¹Ÿå¿…é¡»ç­‰åˆ°5sä¹‹åæ‰èƒ½ä¾æ¬¡æ¨å‡ºã€‚

```kotlin
fun main() {
    var previous = Thread.currentThread()
    repeat(10) {
        val th = Thread(Join.Domino(previous), "$it")
        th.start()
        previous = th
    }
    TimeUnit.SECONDS.sleep(5)
    println("${Thread.currentThread().name} terminate.")
}
```

è¾“å‡ºå¦‚ä¸‹ï¼š

```shell
main terminate.
0 terminate.
1 terminate.
2 terminate.
3 terminate.
4 terminate.
5 terminate.
6 terminate.
7 terminate.
8 terminate.
9 terminate.
```

ä¸‹é¢æ˜¯jdkæºç ä¸­joinçš„å®ç°ï¼š

```java 
public final synchronized void join(final long millis)
throws InterruptedException {
	if (millis > 0) {
		if (isAlive()) {
			final long startTime = System.nanoTime();
			long delay = millis;
			do {
				wait(delay);
			} while (isAlive() && (delay = millis -
					TimeUnit.NANOSECONDS.toMillis(System.nanoTime() - startTime)) > 0);
		}
	} else if (millis == 0) {
		while (isAlive()) {
			wait(0);
		}
	} else {
		throw new IllegalArgumentException("timeout value is negative");
	}
}
```

å¯ä»¥çœ‹åˆ°ï¼Œæœ€ç»ˆè°ƒç”¨çš„è¿˜æ˜¯`wait()`ï¼Œå¹¶ä¸”`join()`æœ¬èº«å°±æ˜¯syncfhronizedçš„ã€‚è¿™å’Œä¹‹å‰[[Study Log/java_kotlin_study/concurrency_art/4_3_inter_thread_communication_1#4.3.2 Wait & Notify|4_3_inter_thread_communication_1]]ä¸­ä»‹ç»çš„Wait \& Notifyæœºåˆ¶æ˜¯ä¸€æ ·çš„ã€‚ 

å½“ç›®æ ‡çº¿ç¨‹ç»“æŸçš„æ—¶å€™ï¼Œå®ƒä¼šè°ƒç”¨`notifyAll()`ï¼Œæ¥é€šçŸ¥ä¹‹å‰è°ƒç”¨äº†joinè€Œå¯¼è‡´waitçš„çº¿ç¨‹ï¼Œç„¶åå”¤é†’å®ƒã€‚

- [ ] #TODO hotspotåœ¨è¿™é‡Œæ³¨å†Œwaitçš„æ—¶å€™ç”¨äº†ä¸€å †éå¸¸ç‚«é…·çš„å®å®šä¹‰è¿˜æœ‰templateã€‚éƒ½åœ¨`jdk/src/hotspot/share/classfile/vmSymbols.hpp`ä¸­ã€‚æœ‰æ—¶é—´åˆ†æä¸€ä¸‹ã€‚ â¬

### 4.3.5 ThreadLocal

ç½‘ä¸Šæœ‰å¾ˆå¤šå„ç§ä»‹ç»ThreadLocalçš„ï¼Œä½†æ˜¯æˆ‘ä¸€ç›´å°±æ˜¯æ²¡å¼„æ˜ç™½åˆ°åº•ä»€ä¹ˆæ—¶å€™æ‰éœ€è¦ç”¨åˆ°è¿™ä¸ªä¸œè¥¿ã€‚å¦å¤–ï¼Œæˆ‘è‡ªå·±æŸ¥äº†ä¸€ä¸‹ï¼Œæˆ‘å·¥ä½œçš„å…¬å¸çš„é¡¹ç›®ä¸­ï¼Œå‡ ç™¾ä¸‡è¡Œä»£ç é‡Œä¹Ÿæ ¹æœ¬æ²¡æœ‰ThreadLocalçš„å½±å­ã€‚

ä¸€ä¸ªä¾‹å­æ˜¯è¿™æ ·çš„ï¼š[java - When and how should I use a ThreadLocal variable? - Stack Overflow](https://stackoverflow.com/questions/817856/when-and-how-should-i-use-a-threadlocal-variable)

æ ¹æ®è¿™é‡Œé¢çš„å›ç­”ï¼Œæˆ‘çš„æ„Ÿè§‰æ˜¯ï¼š

<font color="yellow">å¦‚æœä½ å‘ç°ï¼ŒæŸäº›ã€æ¯ä¸ªçº¿ç¨‹éƒ½æœ‰è‡ªå·±çš„ã€çš„å˜é‡ï¼Œå¦‚æœä½ ä¸æ–¹ä¾¿å®šä¹‰åœ¨ä½ è‡ªå·±çš„xxxThreadé‡Œçš„è¯ï¼Œé‚£ä¹ˆThreadLocalå°±æ´¾ä¸Šç”¨åœºäº†ã€‚</font>

```kotlin
class LocalThread : Thread() {
	var value = 0
	override fun run() {
		value++
		publicValue++
	}
}
```

å°±è¿™ä¸ªä¾‹å­ã€‚è¿™ä¸ªvalueæ˜¯æ¯ä¸ªThreadéƒ½æœ‰çš„ã€‚é‚£ä¹ˆä½ æ”¹å˜äº†th1çš„valueï¼Œth2çš„valueè‚¯å®šä¸ä¼šå—åˆ°å½±å“ï¼›ä½†æ˜¯ï¼Œéš”å£çš„è¿™ä¸ªpublicValueå› ä¸ºä¸åœ¨Threadé‡Œé¢ï¼Œæ‰€ä»¥è‡ªç„¶ä¼šè¢«å¤šä¸ªçº¿ç¨‹è®¿é—®åˆ°åŒä¸€ä¸ªä¸œè¥¿ã€‚

å¦‚æœä½ è¯´ï¼Œè¿™ä¸ªpublicValueå®ƒï¼š

* ä¸æ–¹ä¾¿å†™åœ¨LocalThreadç±»é‡Œé¢ï¼Œå› ä¸ºæˆ‘æœ‰å…¶å®ƒçš„æ“ä½œä¹Ÿä¼šæ¶‰åŠåˆ°è¿™ä¸ªå˜é‡ï¼›
* è¿™ä¸ªå˜é‡æ¯ä¸ªçº¿ç¨‹éƒ½æ˜¯æœ‰è‡ªå·±çš„ä¸€ä»½çš„ã€‚æ¯ä¸ªçº¿ç¨‹<u>æœ‰æƒåˆ©é˜»æ­¢</u>å…¶å®ƒçº¿ç¨‹å¹²æ‰°è¿™ä¸ªå˜é‡çš„çŠ¶æ€ã€‚

> [!comment] æœ‰æƒåˆ©é˜»æ­¢
> æˆ‘æ—¢ç„¶æ˜¯è¯´çš„ã€æœ‰æƒåˆ©ã€ï¼Œé‚£ä¹ˆè‚¯å®šå°±æ˜¯ä¹Ÿå¯ä»¥ä¸é˜»æ­¢

é‚£ä¹ˆå°±å¯ä»¥å®šä¹‰æˆThreadLocalã€‚è‡³äºç”¨æ³•å’Œå†…éƒ¨å®ç°ï¼Œå¯ä»¥ç¨å¾®çœ‹ä¸€çœ‹å…«è‚¡æ–‡ï¼š[Javaå¹¶å‘å¸¸è§é¢è¯•é¢˜æ€»ç»“ï¼ˆä¸‹ï¼‰](https://javaguide.cn/java/concurrent/java-concurrent-questions-03.html)

---

```dataviewjs
const pages = dv.pages('"Study Log/java_kotlin_study/concurrency_art"')
let nextChapterHead = undefined
let res = undefined
const current = dv.current()
for (let page of pages) {
	if (page.chapter_root == true && page.order == Number(current.chapter) + 1) {
		console.log("found next head: " + page.name)
		nextChapterHead = page
		continue
	}
	if (page.chapter == undefined || page.chapter != current.chapter) {
		console.log("not current chapter: " + page.file.name)
		continue
	}
	if (page.order == Number(current.order) + 1) {
		res = page
	}
}
console.log("res: " + res)
console.log("next: " + nextChapterHead)
if (res == undefined) {
	res = nextChapterHead
}
let text = ""
if (res != undefined) {
	const path = res.file.path
	const title = res.title
	const decoLink = "[[" + path + "|" + title + "]]"
	text = "Next Article: " + decoLink
} else {
	text = "æ—…é€”çš„ç»ˆç‚¹ï¼"
}
dv.el("p", text, { attr: { align: "right" } })
```